odoo/addons/product_packaging_container_deposit/README.rst
odoo/addons/product_packaging_container_deposit/__init__.py
odoo/addons/product_packaging_container_deposit/__manifest__.py
odoo/addons/product_packaging_container_deposit/i18n/es.po
odoo/addons/product_packaging_container_deposit/i18n/fr.po
odoo/addons/product_packaging_container_deposit/i18n/it.po
odoo/addons/product_packaging_container_deposit/i18n/product_packaging_container_deposit.pot
odoo/addons/product_packaging_container_deposit/models/__init__.py
odoo/addons/product_packaging_container_deposit/models/container_deposit_order_line_mixin.py
odoo/addons/product_packaging_container_deposit/models/container_deposit_order_mixin.py
odoo/addons/product_packaging_container_deposit/models/product_product.py
odoo/addons/product_packaging_container_deposit/models/stock_package_type.py
odoo/addons/product_packaging_container_deposit/readme/CONTRIBUTORS.rst
odoo/addons/product_packaging_container_deposit/readme/DESCRIPTION.rst
odoo/addons/product_packaging_container_deposit/static/description/icon.png
odoo/addons/product_packaging_container_deposit/static/description/index.html
odoo/addons/product_packaging_container_deposit/tests/__init__.py
odoo/addons/product_packaging_container_deposit/tests/common.py
odoo/addons/product_packaging_container_deposit/tests/fake_models.py
odoo/addons/product_packaging_container_deposit/tests/test_container_deposit_order_mixin.py
odoo/addons/product_packaging_container_deposit/tests/test_product_packaging_container_deposit.py
odoo/addons/product_packaging_container_deposit/views/stock_package_type_views.xml
odoo_addon_product_packaging_container_deposit-16.0.1.2.1.dist-info/METADATA
odoo_addon_product_packaging_container_deposit-16.0.1.2.1.dist-info/WHEEL
odoo_addon_product_packaging_container_deposit-16.0.1.2.1.dist-info/top_level.txt
odoo_addon_product_packaging_container_deposit-16.0.1.2.1.dist-info/RECORD
