Metadata-Version: 2.1
Name: odoo-addon-product_packaging_container_deposit
Version: 16.0.1.2.1
Summary: Add container deposit fees in a order
Home-page: https://github.com/OCA/product-attribute
Author: Camptocamp, BCIM, Odoo Community Association (OCA)
Author-email: support@odoo-community.org
License: AGPL-3
Classifier: Programming Language :: Python
Classifier: Framework :: Odoo
Classifier: Framework :: Odoo :: 16.0
Classifier: License :: OSI Approved :: GNU Affero General Public License v3
Classifier: Development Status :: 4 - Beta
Requires-Python: >=3.10
Requires-Dist: odoo-addon-product-packaging-level<16.1dev,>=16.0dev
Requires-Dist: odoo<16.1dev,>=16.0a
